{
  "Ads": [
    {
      "select_main_ads": "ADMOB",
      "select_backup_ads":"APPLOVIN-M",
      "main_ads_banner": "ca-app-pub-3539400195587863/5526226670",
      "main_ads_intertitial":"ca-app-pub-3539400195587863/1990020936",
      "main_ads_natives":"ca-app-pub-3539400195587863/2612853377",
      "main_ads_rewards":"",
      "backup_ads_natives":"",
      "backup_ads_banner":"db4d5e8718b97d78",
      "backup_ads_intertitial":"518cd97722c60b52",
      "backup_ads_rewards":"",
      "open_ads_admob":"ca-app-pub-3539400195587863/3890276024",
      "open_ads_alien":"",
      "switch_open_ads":"1",
      "switch_banner_natives_ads":"",
      "interval_intertitial": 5,
      "initialize_sdk":"107355779",
      "initialize_sdk_backup_ads":"",
      "high_paying_keyword_1": "",
      "high_paying_keyword_2": "",
      "high_paying_keyword_3": "",
      "high_paying_keyword_4": "",
      "high_paying_keyword_5": "",
      "status_app": "0",
      "link_redirect": "https://"
    }
  ],
  "Categories": [
    {
      "id": 1,
      "name_category": "Ariana Grande",
      "image": "file:///android_asset/image/ArianaGrande.jpg"
    }
  ],
  "Data": [
    {
      "id": 1,
      "name_category": "Ariana Grande",
      "title": "7 rings",
      "image": "file:///android_asset/image/ArianaGrande.jpg",
      "link_mp3": "mp3/7-rings.mp3",
      "lyrics": "<p style=\"text-align: center;\"><font color=#000000>Yeah<br>Breakfast at Tiffany's and bottles of bubbles<br>Girls with tattoos who like getting in trouble<br>Lashes and diamonds, ATM machines<br>Buy myself all of my favorite things<br><br>Yeah<br>Been through some bad shit, I should be a sad bitch<br>Who would have thought it'd turn me to a savage?<br>Rather be tied up with calls and not strings<br>Write my own checks like I write what I sing<br><br>My wrist, stop watchin'<br>My neck is flossy<br>Make big deposits<br>My gloss is poppin'<br><br>You like my hair?<br>Gee, thanks! Just bought it<br>I see it, I like it<br>I want it, I got it<br>Yeah<br><br>I want it, I got it<br>I want it, I got it<br>I want it, I got it<br>I want it, I got it<br><br>You like my hair?<br>Gee, thanks! Just bought it<br>I see it, I like it<br>I want it, I got it<br>Yeah<br><br>Wearin' a ring but ain't gon' be no &quot;Mrs.&quot;<br>Bought matching diamonds for six of my bitches<br>I'd rather spoil all my friends with my riches<br>Think retail therapy my new addiction<br><br>Whoever said money can't solve your problems<br>Must not have had enough money to solve 'em<br>They say, &quot;Which one?&quot; I say, &quot;Nah, I want all 'em&quot;<br>Happiness is the same price as &quot;red-bottoms&quot;<br><br>My smile is beamin'<br>My skin is gleamin'<br>The way it shine<br>I know you've seen it<br>You've seen it<br><br>I bought a crib<br>Just for the closet<br>Both his and hers<br>I want it, I got it<br>Yeah<br><br>I want it, I got it<br>I want it, I got it<br>I want it, I got it<br>I want it, I got it<br>Baby<br><br>You like my hair?<br>Gee, thanks! Just bought it<br>Oh, yeah<br>I see it, I like it<br>I want it, I got it<br>Yep<br><br>Yeah, my receipts be lookin' like phone numbers<br>If it ain't money, then wrong number<br>Black Card is my business card<br>The way it be settin' the tone for me<br><br>I don't mean to brag<br>But I be like, &quot;Put it in the bag&quot;<br>Yeah<br>When you see them racks<br>They stacked up like my ass<br>Yeah<br><br>Shoot<br>Go from the store to the booth<br>Make it all back in one loop<br>Gimme the loot<br>Never mind, I got the juice<br>Nothin' but net when we shoot<br><br>Look at my neck<br>Look at my jet<br>Ain't got enough money to pay me respect<br>Ain't no budget when I'm on the set<br>If I like it then that's what I get<br>Yeah<br><br>I want it, I got it<br>I want it, I got it<br>Yeah<br>I want it, I got it<br>I want it, I got it<br>Oh, yeah, yeah<br><br>You like my hair?<br>Gee, thanks! Just bought it<br>I see it, I like it<br>I want it, I got it<br>Yeah</font></p>"
    },

    {
      "id": 2,
      "name_category": "Ariana Grande",
      "title": "34+35",
      "image": "file:///android_asset/image/ArianaGrande.jpg",
      "link_mp3": "mp3/34+35.mp3",
      "lyrics": "<p style=\"text-align: center;\"><font color=#000000>You might think I'm crazy<br>The way I been craving<br>If I put it quite plainly<br>Just gimme them babies<br><br>So what you doing tonight?<br>Better say &quot;Doing you right&quot;<br>Watching movies but we ain't seen a thing tonight<br><br>I don't wanna keep you up (You up)<br>But show me can you keep it up (It up)<br>'Cause then I'll have to keep you up<br>Shit maybe I'ma keep you up, boy<br><br>I been drinking coffee (I been drinking coffee)<br>And I been eating healthy (And I been eating healthy)<br>You know I keep it squeaky, yeah (You know I keep it squeaky)<br>Saving up my energy (Saving up my energy)<br><br>Can you stay up all night?<br>Fuck me 'til the daylight<br>34+35<br>Can you stay up all night?<br>Fuck me 'til the daylight<br>34+35<br><br>You drink it just like water (Water)<br>You say it taste like candy<br>So what you doing tonight? (Tonight)<br>Better say &quot;Doing you right&quot; (Alright)<br>Watching movies but we ain't seen a thing tonight<br><br>I don't wanna keep you up (You up)<br>But show me can you keep it up (It up)<br>'Cause then I'll have to keep you up<br>Shit maybe I'ma keep you up, boy<br><br>I been drinking coffee (I been drinking coffee)<br>And I been eating healthy (And I been eating healthy)<br>You know I keep it squeaky, yeah<br>Saving up my energy (Yeah, yeah, yeah)<br><br>Can you stay up all night?<br>Fuck me 'til the daylight<br>34+35<br>Can you stay up all night?<br>Fuck me 'til the daylight<br>34+35<br><br>Baby, you might need a seatbelt when I ride it<br>I'ma leave it open like a door, come inside it<br>Even though I'm wifey you can hit it like a side chick<br>Don't need no side dick, no<br><br>Got the neighbors yelling &quot;Earthquake&quot; (Earthquake)<br>4.5 when I make the bed shake (Bed shake)<br>Put it down heavy even though it's lightweight (It's lightweight, yeah, yeah)<br><br>We started at midnight<br>Go 'til the sunrise<br>Done at the same time<br>But who's counting the time when we got it for life (Got it for life)<br><br>I know all your favorite spots (Favorite spots)<br>We can take it from the top (From the top)<br>You're such a dream come true, true<br>Make a bitch wanna hit snooze, ooh<br><br>Can you stay up all night?<br>Fuck me 'til the daylight<br>34+35 (34+35)<br>Can you stay up all night?<br>Fuck me 'til the daylight<br>34+35<br><br>Means I wanna 69 witcha<br>No shit<br>Math class<br>Never was good</font></p>"
    },
	
	{
      "id": 3,
      "name_category": "Ariana Grande",
      "title": "Bang Bang",
      "image": "file:///android_asset/image/ArianaGrande.jpg",
      "link_mp3": "mp3/Bang-Bang.mp3",
      "lyrics": "<p style=\"text-align: center;\"><font color=#000000>[Verse 1 - Jessie J:]<br>She got a body like an hour glass<br>But I can give it to you all the time<br>She got a booty like a Cadillac<br>But I can send you into overdrive (oh)<br><br>(You've been waiting for that...<br>Step on up swing your bat)<br>See anybody could be bad to you,<br>You need a good girl to blow your mind, yeah<br><br>[Chorus - Jessie J:]<br>Bang bang into the room (I know ya want it)<br>Bang bang all over you (I'll let ya have it)<br>Wait a minute lemme take you there (ah)<br>Wait a minute till ya (ah)<br>Bang bang there goes your heart (I know ya want it)<br>Back, back seat of my car (I'll let ya have it)<br>Wait a minute lemme take you there (ah)<br>Wait a minute till ya (ah)<br><br>[Verse 2 - Ariana Grande:]<br>She might've let you hold her hand in school<br>But I'm a show you how to graduate<br>No, I don't need to hear you talk the talk<br>Just come and show me what your momma gave (oh, yeah)<br><br>(Okay you've got a very big shhh,<br>Mouth but don't say a thing)<br>See anybody could be good to you,<br>You need a bad girl to blow your mind<br><br>[Chorus:]<br>Bang bang into the room (I know ya want it)<br>Bang bang all over you (I'll let ya have it)<br>Wait a minute lemme take you there (ah)<br>Wait a minute till ya (ah)<br>Bang bang there goes your heart (I know ya want it)<br>Back, back seat of my car (I'll let ya have it)<br>Wait a minute lemme take you there (ah)<br>Wait a minute till ya (ah)<br><br>[Verse 3 - Nicki Minaj:]<br>(You know what, girls?<br>Let me show you how to do.)<br>It's Myx Moscato<br>It's frizz in a bottle<br>It's Nicki full throttle<br>It's oh, oh.<br>Swimming in the grotto<br>We winning in the lotto<br>We dipping in the pot of blue foam<br>Kitten so good<br>It's drippin' on wood<br>Get a ride in the engine that could go<br>Batman Robin it<br>Bang, bang, cocking it<br>Queen Nicki dominant, prominent<br>It's me, Jessie, and Ari<br>If they test me they sorry<br>Ride his uh like a Harley<br>Then pull off in this Ferrari<br>If he hangin' we bangin'<br>Phone rangin', he slangin'<br>It ain't karaoke night but get the mic 'cause I'm singing (uh)<br><br>B to da' A to da' N to da' G to da' uh (baby)<br>B to da' A to da' N to da' G to da' hey<br>See anybody could be good to you,<br>You need a bad girl to blow your mind (your mind)<br><br>[Chorus:]<br>Bang bang into the room (I know ya want it)<br>Bang bang all over you (I'll let ya have it)<br>Wait a minute lemme take you there (ah)<br>Wait a minute till ya (ah)<br>Bang bang there goes your heart (I know ya want it)<br>Back, back seat of my car (I'll let ya have it)<br>Wait a minute lemme take you there (ah)<br>Wait a minute till ya (ah)<br><br>[Outro - Nicki Minaj (overlapping):]<br>Bang bang into the room (I know ya want it)<br>Bang bang all over you (I'll let ya have it)<br><br>[Nicki Minaj:]<br>Yo, I said bang, bang, bang, bang, bang, bang<br>Bang, bang, bang, bang, bang, bang, bang<br><br>[Jessie J:]<br>Bang bang there goes your heart (I know ya want it)<br>Back, back seat of my car (I'll let ya have it)<br>Wait a minute lemme take you there (ah)<br>Wait a minute till ya (ah)<br></font></p>"
    },
	
	{
      "id": 4,
      "name_category": "Ariana Grande",
      "title": "boyfriend",
      "image": "file:///android_asset/image/ArianaGrande.jpg",
      "link_mp3": "mp3/boyfriend.mp3",
      "lyrics": "<p style=\"text-align: center;\"><font color=#000000>[Ariana Grande:]<br>I'm a motherfuckin' train wreck<br>I don't wanna be too much<br>But I don't wanna miss your touch<br>And you don't seem to give a fuck<br>I don't wanna keep you waiting<br>But I do just what I have to do<br>And I might not be the one for you<br>But you ain't about to have no boo<br><br>'Cause I know we be so complicated<br>But we be so smitten, it's crazy<br>I can't have what I want, but neither can you<br><br>You ain't my boyfriend (Boyfriend)<br>And I ain't your girlfriend (Girlfriend)<br>But you don't want me to see nobody else<br>And I don't want you to see nobody<br>But you ain't my boyfriend (Boyfriend)<br>And I ain't your girlfriend (Girlfriend)<br>But you don't want me to touch nobody else<br>Baby, we ain't gotta tell nobody<br><br>[Mikey:]<br>Even though you ain't mine, I promise the way we fight<br>Make me honestly feel like we just in love<br>'Cause, baby, when push comes to shove<br>Damn, baby, I'm a train wreck too (Too)<br>I lose my mind when it comes to you<br>I take time with the ones I choose<br>And I don't want a smile if it ain't from you, yeah<br><br>I know we'd be so complicated<br>Lovin' you sometimes drive me crazy<br>'Cause I can't have what I want and neither can you<br><br>[Ariana Grande:]<br>You ain't my boyfriend (Boyfriend)<br>And I ain't your girlfriend (Girlfriend)<br>But you don't want me to see nobody else<br>And I don't want you to see nobody<br>But you ain't my boyfriend (Boyfriend)<br>And I ain't your girlfriend (Girlfriend)<br>But you don't want me to touch nobody else<br>Baby, we ain't gotta tell nobody<br><br>[Scootie (Ariana Grande):]<br>I wanna kiss you (Yeah), don't wanna miss you (Yeah)<br>But I can't be with you 'cause I got issues<br>Yeah, on the surface, seem like it's easy<br>Careful with words, but it's still hard to read me<br>Stress high when the trust low (Mmm)<br>Bad vibes, where'd the fun go? (Oh)<br>Try to open up and love more (Love more)<br>Try to open up and love more<br><br>[Scootie &amp; Ariana Grande:]<br>If you were my boyfriend<br>And you were my girlfriend<br>I probably wouldn't see nobody else<br>But I can't guarantee that by myself<br><br>[Ariana Grande:]<br>You ain't my boyfriend (Boyfriend, you ain't my boyfriend)<br>And I ain't your girlfriend (Girlfriend, I ain't your girlfriend)<br>But you don't want me to see nobody else (Nobody)<br>And I don't want you to see nobody<br>But you ain't my boyfriend (Boyfriend, you know you ain't my boyfriend)<br>And I ain't your girlfriend (Girlfriend, yeah, mmm)<br>But you don't want me to touch nobody else (Nobody)<br>Baby, we ain't gotta tell nobody (Oh yeah)<br>You ain't my boyfriend (Boyfriend)<br>And I ain't your girlfriend (Girlfriend)<br>But you don't want me to see nobody else<br>And I don't want you to see nobody<br>But you ain't my boyfriend (Boyfriend)<br>And I ain't your girlfriend (Girlfriend, yeah)<br>But you don't want me to touch nobody else (Nobody)<br>Baby, we ain't gotta tell nobody</font></p>"
    },
	
	{
      "id": 5,
      "name_category": "Ariana Grande",
      "title": "Dangerous Woman",
      "image": "file:///android_asset/image/ArianaGrande.jpg",
      "link_mp3": "mp3/Dangerous-Woman.mp3",
      "lyrics": "<p style=\"text-align: center;\"><font color=#000000>Oh, yeah<br><br>Don't need permission<br>Made my decision to test my limits<br>'Cause it's my business, God as my witness<br>Start what I finished<br>Don't need no hold up<br>Taking control of this kind of moment<br>I'm locked and loaded<br>Completely focused, my mind is open<br><br>All that you got, skin to skin, oh my God<br>Don't ya stop, boy<br><br>Somethin' 'bout you makes me feel like a dangerous woman<br>Somethin' 'bout, somethin' 'bout, somethin' 'bout you<br>Makes me wanna do things that I shouldn't<br>Somethin' 'bout, somethin' 'bout, somethin' 'bout<br><br>Nothing to prove and<br>I'm bulletproof and<br>Know what I'm doing<br>The way we're movin' like introducing<br>Us to a new thing<br>I wanna savor, save it for later<br>The taste, the flavor, 'cause I'm a taker<br>'Cause I'm a giver, it's only nature<br>I live for danger<br><br>All that you got, skin to skin, oh my God<br>Don't ya stop, boy<br><br>Somethin' 'bout you makes me feel like a dangerous woman<br>Somethin' 'bout, somethin' 'bout, somethin' 'bout you<br>Makes me wanna do things that I shouldn't<br>Somethin' 'bout, somethin' 'bout, somethin' 'bout you<br><br>All girls wanna be like that<br>Bad girls underneath, like that<br>You know how I'm feeling inside<br>Somethin' 'bout, somethin' 'bout<br>All girls wanna be like that<br>Bad girls underneath, like that<br>You know how I'm feeling inside<br>Somethin' 'bout, somethin' 'bout<br><br>Somethin' 'bout you makes me feel like a dangerous woman<br>Somethin' 'bout, somethin' 'bout, somethin' 'bout you<br>Makes me wanna do things that I shouldn't<br>Somethin' 'bout, somethin' 'bout, somethin' 'bout you<br><br>All girls wanna be like that<br>Bad girls underneath like that<br>You know how I'm feeling inside<br>Somethin' 'bout, somethin' 'bout<br>All girls wanna be like that<br>Bad girls underneath like that<br>You know how I'm feeling inside<br>Somethin' 'bout, somethin' 'bout<br><br>Yeah, there's somethin' 'bout you boy<br>Yeah, there's somethin' 'bout you boy<br>Yeah, there's somethin' 'bout you boy<br>(somethin' 'bout, somethin' 'bout, somethin' 'bout you)<br>Yeah, there's somethin' 'bout you boy<br>Yeah, there's somethin' 'bout you boy<br>Yeah, there's somethin' 'bout you boy<br>(somethin' 'bout, somethin' 'bout, somethin' 'bout you)</font></p>"
    },
	
	{
      "id": 6,
      "name_category": "Ariana Grande",
      "title": "God is a woman",
      "image": "file:///android_asset/image/ArianaGrande.jpg",
      "link_mp3": "mp3/God-is-a-woman.mp3",
      "lyrics": "<p style=\"text-align: center;\"><font color=#000000>You, you love it how I move you<br>You love it how I touch you<br>My one, when all is said and done<br>You'll believe God is a woman<br>And I, I feel it after midnight<br>A feeling that you can't fight<br>My one, it lingers when we're done<br>You'll believe God is a woman<br><br>I don't wanna waste no time, yeah<br>You ain't got a one-track mind, yeah<br>Have it any way you like, yeah<br>And I can tell that you know I know how I want it<br>Ain't nobody else can relate<br>Boy, I like that you ain't afraid<br>Baby, lay me down and let's pray<br>I'm tellin' you the way I like it, how I want it<br><br>(Yeah)<br>And I can be all the things you told me not to be<br>(Yeah)<br>When you try to come for me, I keep on flourishing<br>(Yeah)<br>And he see the universe when I'm in company<br>It's all in me<br><br>You, you love it how I move you<br>You love it how I touch you<br>My one, when all is said and done<br>You'll believe God is a woman<br>And I, I feel it after midnight<br>A feeling that you can't fight<br>My one, it lingers when we're done<br>You'll believe God is a woman<br><br>I tell you all the things you should know<br>So, baby, take my hand, save your soul<br>We can make it last, take it slow, hmm<br>And I can tell that you know I know how I want it, yeah<br>That you different from the rest<br>And boy, if you confess, you might get blessed<br>See if you deserve what comes next<br>I'm tellin' you the way I like it, how I want it<br><br>(Yeah)<br>And I can be all the things you told me not to be<br>(Yeah)<br>When you try to come for me, I keep on flourishing<br>(Yeah)<br>And he see the universe when I'm in company<br>It's all in me<br><br>You, you love it how I move you<br>You love it how I touch you<br>My one, when all is said and done<br>You'll believe God is a woman<br>And I, I feel it after midnight<br>A feeling that you can't fight<br>My one, it lingers when we're done<br>You'll believe God is a woman, yeah, yeah<br><br>(God is a woman)<br>Yeah, yeah<br>(God is a woman, yeah)<br>My one<br>(One)<br>When all is said and done<br>You'll believe God is a woman<br>You'll believe God<br>(God is a woman)<br>Oh, yeah<br>(God is a woman, yeah)<br>(One)<br>It lingers when we're done<br>You'll believe God is a woman<br></font></p>"
    },
	
	{
      "id": 7,
      "name_category": "Ariana Grande",
      "title": "Into You",
      "image": "file:///android_asset/image/ArianaGrande.jpg",
      "link_mp3": "mp3/Into-You.mp3",
      "lyrics": "<p style=\"text-align: center;\"><font color=#000000>I'm so into you, I can barely breathe<br>And all I wanna do is to fall in deep<br>But close ain't close enough 'til we cross the line, hey, yeah<br>So name a game to play, and I'll roll a dice, hey<br><br>Oh, baby, look what you started<br>The temperature's rising in here<br>Is this gonna happen?<br>Been waiting and waiting for you to make a move<br>(Woo, oh, oh, oh)<br>Before I make a move<br>(Woo, oh, oh, oh)<br><br>So, baby, come light me up, and maybe I'll let you on it<br>A little bit dangerous, but, baby, that's how I want it<br>A little less conversation and a little more &quot;touch my body&quot;<br>'Cause I'm so into you, into you, into you<br>Got everyone watchin' us, so, baby, let's keep it secret<br>A little bit scandalous, but, baby, don't let them see it<br>A little less conversation and a little more &quot;touch my body&quot;<br>'Cause I'm so into you, into you, into you, oh yeah<br><br>This could take some time, hey<br>I made too many mistakes<br>Better get this right, right, baby<br><br>Oh, baby, look what you started<br>The temperature's rising in here<br>Is this gonna happen?<br>Been waiting and waiting for you to make a move<br>(Woo, oh, oh, oh)<br>Before I make a move<br>(Woo, oh, oh, oh)<br><br>So, baby, come light me up, and maybe I'll let you on it<br>A little bit dangerous, but, baby, that's how I want it<br>A little less conversation and a little more &quot;touch my body&quot;<br>'Cause I'm so into you, into you, into you<br>Got everyone watchin' us, so, baby, let's keep it secret<br>A little bit scandalous, but, baby, don't let them see it<br>A little less conversation and a little more &quot;touch my body&quot;<br>'Cause I'm so into you, into you, into you<br><br>Tell me what you came here for?<br>'Cause I can't, I can't wait no more<br>I'm on the edge with no control<br>And I need, I need you to know<br>You to know, oh<br><br>So, baby, come light me up, and maybe I'll let you on it<br>A little bit dangerous, but, baby, that's how I want it<br>A little less conversation and a little more &quot;touch my body&quot;<br>'Cause I'm so into you, into you, into you<br>Got everyone watchin' us, so, baby, let's keep it secret<br>A little bit scandalous, but, baby, don't let them see it<br>A little less conversation and a little more &quot;touch my body&quot;<br>'Cause I'm so into you, into you, into you<br><br>So come light me up, so come light me up, my baby<br>Little dangerous, a little dangerous, my boy<br>A little less conversation and a little more &quot;touch my body&quot;<br>'Cause I'm so into you, into you, into you</font></p>"
    },
	
	{
      "id": 8,
      "name_category": "Ariana Grande",
      "title": "Love Me Harder",
      "image": "file:///android_asset/image/ArianaGrande.jpg",
      "link_mp3": "mp3/Love-Me-Harder.mp3",
      "lyrics": "<p style=\"text-align: center;\"><font color=#000000>[Ariana Grande:]<br>Tell me something I need to know<br>Then take my breath and never let it go<br>If you just let me invade your space<br>I'll take the pleasure, take it with the pain<br><br>And if in the moment I bite my lip<br>Baby, in that moment you'll know this is<br>Something bigger than us and beyond bliss<br>Give me a reason to believe it<br><br>'Cause if you want to keep me, you gotta, gotta, gotta, gotta, got to love me harder<br>And if you really need me, you gotta, gotta, gotta, gotta, got to love me harder<br>Baby, love me harder<br>Ooh, ooh, ooh, ooh<br>Love me, love me, love me<br>Ooh, ooh, ooh, ooh<br>Harder, harder, harder<br><br>[The Weeknd:]<br>I know your motives and you know mine<br>The ones that love me, I tend to leave behind<br>If you know about me and choose to stay<br>Then take this pleasure and take it with the pain<br><br>And if in the moment you bite your lip<br>When I get you moaning you know it's real<br>Can you feel the pressure between your hips?<br>I'll make it feel like the first time<br><br>[Ariana Grande &amp; The Weeknd:]<br>'Cause if you want to keep me, you gotta, gotta, gotta, gotta, got to love me harder (I'mma love you harder)<br>And if you really need me, you gotta, gotta, gotta, gotta, got to love me harder (love me harder)<br>Ooh, ooh, ooh, ooh<br>Love me, love me, love me<br>Ooh, ooh, ooh, ooh<br>Harder, harder, harder<br>Ooh, ooh, ooh, ooh<br>Love me, love me, love me<br>Ooh, ooh, ooh, ooh<br>Harder, harder, harder<br><br>So what do I do if I can't figure it out (figure it out)?<br>You got to try, try, try again, yeah<br>So what do I do if I can't figure it out (figure it out)?<br>I'm gonna leave, leave, leave again<br><br>'Cause if you want to keep me, you gotta, gotta, gotta, gotta, got to love me harder (I'mma love you, love you, love you)<br>And if you really need me, you gotta, gotta, gotta, gotta, got to love me harder (love me, love me, baby)<br>'Cause if you want to keep me, you gotta, gotta, gotta, gotta, got to love me harder (love me harder)<br>And if you really need me, you gotta, gotta, gotta, gotta, got to love me harder (I'mma love you harder)<br>Ooh, ooh, ooh, ooh<br>Love me, love me, love me<br>Ooh, ooh, ooh, ooh<br>Harder, harder, harder<br>(Love me, love me, baby)<br>Ooh, ooh, ooh, ooh<br>Love me, love me, love me<br>(Just a little bit, harder, harder, baby)<br>Ooh, ooh, ooh, ooh<br>Harder, harder, harder</font></p>"
    },
	
	{
      "id": 9,
      "name_category": "Ariana Grande",
      "title": "no tears left to cry",
      "image": "file:///android_asset/image/ArianaGrande.jpg",
      "link_mp3": "mp3/no-tears-left-to-cry.mp3",
      "lyrics": "<p style=\"text-align: center;\"><font color=#000000>Right now, I'm in a state of mind<br>I wanna be in like all the time<br>Ain't got no tears left to cry<br>So I'm pickin' it up, pickin' it up<br>I'm lovin', I'm livin', I'm pickin' it up<br>So I'm pickin' it up, pickin' it up<br>I'm lovin', I'm livin', I'm pickin' it up (oh, yeah)<br><br>Pickin' it up (yeah), pickin' it up (yeah)<br>Lovin', I'm livin', so we turnin' up<br>Yeah, we turnin' it up<br><br>Ain't got no tears in my body<br>I ran out, but boy, I like it, I like it, I like it<br>Don't matter how, what, when, who tries it<br>We're out here vibin', we vibin', we vibin'<br><br>Comin' out, even when it's rainin' down<br>Can't stop now, can't stop so shut your mouth<br>Shut your mouth, and if you don't know<br>Then now you know it, babe<br>Know it, babe, yeah<br><br>Right now, I'm in a state of mind<br>I wanna be in, like, all the time<br>Ain't got no tears left to cry<br>So I'm pickin' it up, pickin' it up (oh yeah)<br>I'm lovin', I'm livin', I'm pickin' it up<br>Oh, I just want you to come with me<br>We're on another mentality<br>Ain't got no tears left to cry<br>So I'm pickin' it up, pickin' it up (oh yeah)<br>I'm lovin', I'm livin', I'm pickin' it up<br><br>Pickin' it up (yeah), pickin' it up (yeah)<br>Lovin', I'm livin', so we turnin' up<br>Yeah, we turnin' it up<br><br>They point out the colors in you, I see 'em too<br>And boy I like 'em, I like 'em, I like 'em<br>We're way too fly to partake in all this hate<br>We're out here vibin', we're vibin', we're vibin'<br><br>Comin' out, even when it's rainin' down<br>Can't stop now, can't stop so shut your mouth<br>Shut your mouth<br>And if you don't know that now you know it, babe<br>Know it babe, yeah<br><br>Right now, I'm in a state of mind<br>I wanna be in, like, all the time<br>Ain't got no tears left to cry<br>So I'm pickin' it up, I'm pickin' up (oh yeah)<br>I'm lovin', I'm livin', I'm pickin' it up<br>Oh I just want you to come with me<br>We're on another mentality<br>Ain't got no tears left to cry (so don't cry)<br>So I'm pickin' it up, I'm pickin' up (oh yeah)<br>I'm lovin', I'm livin', I'm pickin' it up<br><br>Comin' out, even when it's rainin' down<br>Can't stop now, (umm, ohh...)<br>Shut your mouth<br>Ain't got no tears left to cry<br>Oh yeah, oh yeah<br><br>Oh I just want you to come with me<br>We're on another mentality<br>Ain't got no tears left to cry (cry)<br>So I'm pickin' it up, I'm pickin' up (oh yeah)<br>I'm lovin', I'm livin', I'm pickin' it up<br><br>I'm pickin' it up, I'm pickin' it up<br>Lovin', I'm livin', so we turn it up<br>Yeah, we're turnin' it up</font></p>"
    },
	
	{
      "id": 10,
      "name_category": "Ariana Grande",
      "title": "One Last Time",
      "image": "file:///android_asset/image/ArianaGrande.jpg",
      "link_mp3": "mp3/One-Last-Time.mp3",
      "lyrics": "<p style=\"text-align: center;\"><font color=#000000>I was a liar<br>I gave in to the fire<br>I know I should've fought it<br>At least I'm being honest<br>Feel like a failure<br>'Cause I know that I failed you<br>I should've done you better<br>'Cause you don't want a liar<br><br>And I know, and I know, and I know<br>She gives you everything<br>But, boy, I couldn't give it to you<br>And I know, and I know, and I know<br>That you got everything<br>But I got nothing here without you<br><br>So one last time<br>I need to be the one who takes you home<br>One more time<br>I promise, after that, I'll let you go<br>Baby, I don't care if you got her in your heart<br>All I really care is you wake up in my arms<br>One last time<br>I need to be the one who takes you home<br><br>I don't deserve it<br>I know I don't deserve it<br>But stay with me a minute<br>I swear I'll make it worth it<br>Can't you forgive me?<br>At least just temporarily<br>I know that this is my fault<br>I should've been more careful<br><br>And I know, and I know, and I know<br>She gives you everything<br>But, boy, I couldn't give it to you<br>And I know, and I know, and I know<br>That you got everything<br>But I got nothing here without you, baby<br><br>So one last time<br>I need to be the one who takes you home<br>One more time<br>I promise, after that I'll let you go<br>Baby, I don't care if you got her in your heart<br>All I really care is you wake up in my arms<br>One last time<br>I need to be the one who takes you home (la li he)<br><br>I know I should've fought it<br>At least I'm being honest (yeah)<br>But stay with me a minute<br>I swear I'll make it worth it, babe<br>'Cause I don't wanna be without you<br><br>(Oh)<br>So one last time<br>I need to be the one who takes you home (takes you home, babe)<br>One more time<br>I promise, after that I'll let you go<br>Baby, I don't care if you got her in your heart (babe)<br>All I really care is you wake up in my arms (wake up in my arms)<br>One last time<br>I need to be the one who takes you home (yeah)<br><br>One last time<br>I need to be the one who takes you home</font></p>"
    },
	
	{
      "id": 11,
      "name_category": "Ariana Grande",
      "title": "positions",
      "image": "file:///android_asset/image/ArianaGrande.jpg",
      "link_mp3": "mp3/positions.mp3",
      "lyrics": "<p style=\"text-align: center;\"><font color=#000000>Heaven sent you to me<br>I'm just hoping I don't repeat history<br><br>Boy I'm tryna meet your mama<br>On a Sunday<br>Then make a lotta love<br>On a Monday (Ah, ah)<br>Never need no (No)<br>No one else, babe<br>'Cause I'll be<br><br>Switching them positions for you<br>Cooking in the kitchen and I'm in the bedroom<br>I'm in the Olympics way I'm jumping through hoops<br>Know my love infinite nothing I wouldn't do<br>That I won't do, switching for you<br><br>Perfect, perfect<br>You're too good to be true (You're too good to be true)<br>But I get tired of running<br>Fuck it, now I'm running with you (with you)<br><br>Said boy I'm tryna meet your mama<br>On a Sunday<br>Then make a lotta love<br>On a Monday (Ah, ah)<br>Never need no (No)<br>No one else babe<br>'Cause I'll be<br><br>Switching them positions for you<br>Cooking in the kitchen and I'm in the bedroom<br>I'm in the Olympics way I'm jumping through hoops<br>Know my love infinite nothing I wouldn't do<br>That I won't do, switching for you<br>Cooking in the kitchen and I'm in the bedroom<br>I'm in the Olympics way I'm jumping through hoops<br>Know my love infinite nothing I wouldn't do (nothing)<br>That I won't do, switching for you<br><br>This some shit that I<br>Usually don't do (Yeah)<br>But for you I kinda<br>Kinda want to<br>'Cause you're down for me<br>And I'm down too<br>(And I'm down too)<br>Yeah I'm down too<br>Switching them positions for you<br><br>This some shit that I (Yeah)<br>Usually don't do (Don't do)<br>But for you I kinda<br>Kinda want to<br>'Cause you're down for me<br>And I'm down too<br>('Cause you're down for me)<br><br>Switching them positions for you<br>Cooking in the kitchen and I'm in the bedroom<br>I'm in the Olympics way I'm jumping through hoops (Jumping, jumping)<br>Know my love infinite nothing I wouldn't do<br>That I won't do, switching for you (Ooh whoa)<br>Cooking in the kitchen and I'm in the bedroom<br>I'm in the Olympics way I'm jumping through hoops<br>Know my love infinite nothing I wouldn't do (I wouldn't do)<br>That I won't do, switching for you</font></p>"
    },
	
	{
      "id": 12,
      "name_category": "Ariana Grande",
      "title": "Problem",
      "image": "file:///android_asset/image/ArianaGrande.jpg",
      "link_mp3": "mp3/Problem.mp3",
      "lyrics": "<p style=\"text-align: center;\"><font color=#000000>[Iggy:]<br>Uh huh!<br>It's Iggy Iggs!<br>I got one more problem with you girl<br>One less one less!<br>Problem<br><br>[Ariana Grande:]<br>Hey baby even though I hate ya!<br>I wanna love ya<br>I want you!<br>And even though I can't forgive you<br>I really want ta<br>I want you!<br><br>Tell me, tell me baby<br>Why can't you leave me?<br>'Cause even though I shouldn't want it<br>I gotta have it<br>I want you!<br><br>Head in the clouds<br>Got no weight on my shoulders<br>I should be wiser<br>And realize that I've got<br><br>[Big Sean:]<br>One less problem without ya!<br>I got!<br>One less problem without ya!<br>I got!<br>One less problem without ya!<br>[Ariana Grande:]<br>I got one less, one less problem<br>[Big Sean:]<br>One less problem without ya<br>I got!<br>One less problem without ya!<br>I got!<br>One less problem without ya!<br>[Ariana Grande:]<br>I got one less, one less problem<br><br>[Ariana Grande:]<br>I know you're never gonna wake up<br>I gotta give up<br>But it's you!<br>I know I shouldn't ever call back<br>Or let you come back<br>But it's you!<br>Every time you touch me<br>And say you love me<br>I get a little bit breathless<br>I shouldn't want it<br>But it's you!<br><br>Head in the clouds<br>Got no weight on my shoulders<br>I should be wiser<br>And realize that I've got<br><br>[Big Sean:]<br>One less problem without ya!<br>I got!<br>One less problem without ya!<br>I got!<br>One less problem without ya!<br>[Ariana Grande:]<br>I got one less, one less problem<br>[Big Sean:]<br>One less problem without ya<br>I got!<br>One less problem without ya!<br>I got!<br>One less problem without ya!<br>[Ariana Grande:]<br>I got one less, one less problem<br><br>[Iggy:]<br>It's Iggy Iggs!<br>Uh!<br>What you got?<br>Smart money bettin'<br>I'll be better off without you<br>In no time<br>I'll be forgettin' all about you<br>You saying that you know<br>But I really really doubt you<br>Understand my life is easy<br>When I ain't around you<br>Iggy Iggy<br>Too biggie to be here stressin'<br>I'm thinkin' I love the thought of you<br>More than I love your presence<br>And the best thing now<br>Is probably for you to exit<br>I let you go<br>Let you back<br>I finally learned my lesson!<br>No half-stepping<br>Either you want it or you just playin'<br>I'm listening to you knowin'<br>I can't believe what you're sayin'<br>There's a million you's baby boo<br>So don't be dumb<br>I got 99 problems<br>But you won't be one<br>Like what!<br><br>[Ariana Grande:]<br>One less, one less problem<br>One less, one less problem<br><br>Head in the clouds<br>Got no weight on my shoulders<br>I should be wiser<br>And realize that I've got (I've got)<br><br>[Big Sean:]<br>One less problem without ya!<br>I got!<br>One less problem without ya!<br>I got!<br>One less problem without ya!<br>[Ariana Grande:]<br>I got one less, one less problem<br>[Big Sean:]<br>One less problem without ya<br>I got!<br>One less problem without ya!<br>I got!<br>One less problem without ya!<br>[Ariana Grande:]<br>I got one less, one less problem<br>[Big Sean:]<br>One less problem without ya<br>I got!<br>One less problem without ya!<br>I got!<br>One less problem without ya!<br>[Ariana Grande:]<br>I got one less, one less problem</font></p>"
    },
	
	{
      "id": 13,
      "name_category": "Ariana Grande",
      "title": "Side To Side",
      "image": "file:///android_asset/image/ArianaGrande.jpg",
      "link_mp3": "mp3/Side-To-Side.mp3",
      "lyrics": "<p style=\"text-align: center;\"><font color=#000000>[Ariana Grande &amp; Nicki Minaj:]<br>I've been here all night, Ariana<br>I've been here all day, Nicki Minaj<br>And boy, got me walkin' side to side<br>Let them hoes know<br><br>[Ariana Grande:]<br>I'm talkin' to ya<br>See you standing over there with your body<br>Feeling like I wanna rock with your body<br>And we don't gotta think 'bout nothin' ('bout nothin')<br>I'm comin' at ya<br>'Cause I know you got a bad reputation<br>Doesn't matter, 'cause you give me temptation<br>And we don't gotta think 'bout nothin' ('bout nothin')<br><br>These friends keep talkin' way too much<br>Say I should give you up<br>Can't hear them, no, 'cause I...<br><br>I've been here all night<br>I've been here all day<br>And boy, got me walkin' side to side<br>I've been here all night<br>I've been here all day<br>And boy, got me walkin' side to side (side to side)<br><br>Been tryna hide it<br>Baby, what's it gonna hurt if they don't know?<br>Makin' everybody think that we solo<br>Just as long as you know you got me (you got me)<br>And boy I got ya<br>'Cause tonight I'm making deals with the devil<br>And I know it's gonna get me in trouble<br>Just as long as you know you got me<br><br>These friends keep talkin' way too much<br>Say I should give you up<br>Can't hear them, no, 'cause I...<br><br>I've been here all night<br>I've been here all day<br>And boy, got me walkin' side to side (side to side)<br>I've been here all night<br>(Been here all night, baby)<br>I've been here all day<br>(Been here all day, baby)<br>And boy, got me walkin' side to side (side to side)<br><br>[Nicki Minaj:]<br>This the new style with the fresh type of flow<br>Wrist icicle, ride dick bicycle<br>Come true yo, get you this type of blow<br>If you wanna Minaj I got a tricycle<br><br>All these bitches, flows is my mini-me<br>Body smoking, so they call me young Nicki chimney<br>Rappers in they feelings 'cause they feelin' me<br>Uh, I-I give zero fucks and I got zero chill in me<br>Kissing me, copped the blue box that say Tiffany<br>Curry with the shot, just tell 'em to call me Stephanie<br>Gun pop and I make my gum pop<br>I'm the queen of rap, young Ariana run pop<br><br>[Ariana Grande:]<br>These friends keep talkin' way too much<br>Say I should give him up<br>Can't hear them, no, 'cause I...<br><br>I've been here all night<br>I've been here all day<br>And boy, got me walkin' side to side (side to side)<br>I've been here all night<br>(Been here all night, baby)<br>I've been here all day<br>(Been here all day, baby)<br>Boy, got me walkin' side to side (side to side)<br><br>[Nicki Minaj:]<br>This the new style with the fresh type of flow<br>Wrist icicle, ride dick bicycle<br>Come true yo, get you this type of blow<br>If you wanna Minaj I got a tricycle</font></p>"
    },
	
	{
      "id": 14,
      "name_category": "Ariana Grande",
      "title": "Stuck with U",
      "image": "file:///android_asset/image/ArianaGrande.jpg",
      "link_mp3": "mp3/Stuck-with-U.mp3",
      "lyrics": "<p style=\"text-align: center;\"><font color=#000000>Mm mm mm<br>Hey, yeah<br>(That's just for fun)<br>(What?)<br>(I'm stuck with you)<br>(Hehehe)<br>Ah ah<br><br>I'm not one to stick around<br>One strike and you're out, baby<br>Don't care if I sound crazy<br>But you never let me down, no, no<br>That's why when the sun's up I'm stayin'<br>Still layin' in your bed singin'<br><br>Ooh, ooh, ooh, ooh<br>Got all this time on my hands<br>Might as well cancel our plans, yeah<br>I could stay here for a lifetime<br><br>So lock the door<br>And throw out the key<br>Can't fight this no more<br>It's just you and me<br>And there's nothing I, nothing I, I can do<br>I'm stuck with you, stuck with you, stuck with you<br><br>So go ahead<br>And drive me insane<br>Baby, run your mouth<br>I still wouldn't change<br>Being stuck with you, stuck with you, stuck with you<br>I'm stuck with you, stuck with you, stuck with you, baby<br><br>There's nowhere we need to be, no, no, no<br>I'ma get to know you better<br>Kinda hope we're here forever<br>There's nobody on these streets<br>If you told me that the world's ending<br>Ain't no other way that I could spend it<br><br>Oh, oh, oh, oh<br>Got all this time in my hands<br>Might as well cancel our plans<br>I could stay here forever<br><br>So lock the door<br>And throw out the key<br>Can't fight this no more<br>It's just you and me<br>And there's nothing I, nothing I, I can do<br>I'm stuck with you, stuck with you, stuck with you<br><br>So go ahead<br>And drive me insane<br>Baby, run your mouth<br>I still wouldn't change<br>Being stuck with you, stuck with you, stuck with you<br>I'm stuck with you, stuck with you, stuck with you<br><br>Woah, oh, oh<br>Baby, come take all my time<br>Go on, make me lose my mind<br>We got all that we need here tonight<br><br>I lock the door (Lock the door)<br>And throw out the key<br>Can't fight this no more (Can't fight this no more)<br>It's just you and me<br>And there's nothing I'd, nothing I'd rather do<br>I'm stuck with you, stuck with you, stuck with you<br><br>So go ahead and drive me insane<br>Baby, run your mouth<br>I still wouldn't change all this<br>Lovin' you, hatin' you, wantin' you<br>I'm stuck with you, stuck with you, stuck with<br>You<br>Stuck with you, stuck with you, stuck with you</font></p>"
    },
	
	{
      "id": 15,
      "name_category": "Ariana Grande",
      "title": "thank u, next",
      "image": "file:///android_asset/image/ArianaGrande.jpg",
      "link_mp3": "mp3/thank-u,-next.mp3",
      "lyrics": "<p style=\"text-align: center;\"><font color=#000000>Thought I'd end up with Sean<br>But he wasn't a match<br>Wrote some songs about Ricky<br>Now I listen and laugh<br>Even almost got married<br>And for Pete, I'm so thankful<br>Wish I could say, &quot;Thank you&quot; to Malcolm<br>'Cause he was an angel<br><br>One taught me love<br>One taught me patience<br>And one taught me pain<br>Now, I'm so amazing<br>Say I've loved and I've lost<br>But that's not what I see<br>So, look what I got<br>Look what you taught me<br>And for that, I say<br><br>Thank you, next (Next)<br>Thank you, next (Next)<br>Thank you, next<br>I'm so fuckin' grateful for my ex<br>Thank you, next (Next)<br>Thank you, next (Next)<br>Thank you, next (Next)<br>I'm so fuckin'...<br><br>Spend more time with my friends<br>I ain't worried 'bout nothin'<br>Plus, I met someone else<br>We havin' better discussions<br>I know they say I move on too fast<br>But this one gon' last<br>'Cause her name is Ari<br>And I'm so good with that (So good with that)<br><br>She taught me love (Love)<br>She taught me patience (Patience)<br>How she handles pain (Pain)<br>That shit's amazing (Yeah, she's amazing)<br>I've loved and I've lost (Yeah, yeah)<br>But that's not what I see (Yeah, yeah)<br>'Cause look what I've found (Yeah, yeah)<br>Ain't no need for searching, and for that, I say<br><br>Thank you, next (Thank you, next)<br>Thank you, next (Thank you, next)<br>Thank you, next (Thank you)<br>I'm so fuckin' grateful for my ex<br>Thank you, next (Thank you, next)<br>Thank you, next (Said thank you, next)<br>Thank you, next (Next)<br>I'm so fuckin' grateful for my ex<br><br>Thank you, next<br>Thank you, next<br>Thank you, next<br>I'm so fucking...<br><br>One day I'll walk down the aisle<br>Holding hands with my mama<br>I'll be thanking my dad<br>'Cause she grew from the drama<br>Only wanna do it once, real bad<br>Gon' make that shit last<br>God forbid something happens<br>Least this song is a smash (Song is a smash)<br><br>I've got so much love (Love)<br>Got so much patience (Patience)<br>I've learned from the pain (Pain)<br>I turned out amazing (Turned out amazing)<br>Say I've loved and I've lost (Yeah, yeah)<br>But that's not what I see (Yeah, yeah)<br>'Cause look what I've found (Yeah, yeah)<br>Ain't no need for searching<br>And for that, I say<br><br>Thank you, next (Thank you, next)<br>Thank you, next (Thank you, next)<br>Thank you, next<br>I'm so fuckin' grateful for my ex<br>Thank you, next (Thank you, next)<br>Thank you, next (Said thank you, next)<br>Thank you, next (Next)<br>I'm so fuckin' grateful for my ex<br><br>Thank you, next<br>Thank you, next<br>Thank you, next<br>Yeah, yee<br>Thank you, next<br>Thank you, next<br>Thank you, next<br>Yeah, yee</font></p>"
    }
  ]
}
