{
  "Ads": [
    {
      "select_main_ads": "ADMOB",
      "select_backup_ads":"APPLOVIN-M",
      "main_ads_banner": "ca-app-pub-3940256099942544/6300978111x",
      "main_ads_intertitial":"ca-app-pub-3940256099942544/1033173712x",
      "main_ads_rewards":"",
      "backup_ads_banner":"db4d5e8718b97d78",
      "backup_ads_intertitial":"518cd97722c60b52",
      "backup_ads_rewards":"",
      "interval_intertitial": 5,
      "initialize_sdk":"107355779",
      "initialize_sdk_backup_ads":"",
      "high_paying_keyword_1": "",
      "high_paying_keyword_2": "",
      "high_paying_keyword_3": "",
      "high_paying_keyword_4": "",
      "high_paying_keyword_5": "",
      "status_app": "0",
      "link_redirect": "https://"
    }
  ],
  "Categories": [
    {
      "id": 1,
      "name_category": "Bhool Bhulaiyaa 2",
      "image": "file:///android_asset/image/BhoolBhulaiyaa2.jpg"
    }
  ],
  "Data": [
    {
      "id": 1,
      "name_category": "Bhool Bhulaiyaa 2",
      "title": "Ami Je Tomar",
      "image": "file:///android_asset/image/BhoolBhulaiyaa2.jpg",
      "link_mp3": "mp3/AmiJeTomar.mp3",
      "lyrics": ""
    },

    {
      "id": 2,
      "name_category": "Bhool Bhulaiyaa 2",
      "title": "Bhool Bhulaiyaa 2 Title Track",
      "image": "file:///android_asset/image/BhoolBhulaiyaa2.jpg",
      "link_mp3": "mp3/BhoolBhulaiyaa2TitleTrack.mp3",
      "lyrics": ""
    },
	
	{
      "id": 3,
      "name_category": "Bhool Bhulaiyaa 2",
      "title": "De Taali",
      "image": "file:///android_asset/image/BhoolBhulaiyaa2.jpg",
      "link_mp3": "mp3/DeTaali.mp3",
      "lyrics": ""
    },
	
	{
      "id": 4,
      "name_category": "Bhool Bhulaiyaa 2",
      "title": "Hare Krishna Hare Ram",
      "image": "file:///android_asset/image/BhoolBhulaiyaa2.jpg",
      "link_mp3": "mp3/HareKrishnaHareRam.mp3",
      "lyrics": ""
    },
	
	{
      "id": 5,
      "name_category": "Bhool Bhulaiyaa 2",
      "title": "Hum Nashe Mein Toh Nahin",
      "image": "file:///android_asset/image/BhoolBhulaiyaa2.jpg",
      "link_mp3": "mp3/HumNasheMeinTohNahin.mp3",
      "lyrics": ""
    },
	
	{
      "id": 6,
      "name_category": "Bhool Bhulaiyaa 2",
      "title": "Mere Dholna",
      "image": "file:///android_asset/image/BhoolBhulaiyaa2.jpg",
      "link_mp3": "mp3/MereDholna.mp3",
      "lyrics": ""
    },
	
	{
      "id": 7,
      "name_category": "Bhool Bhulaiyaa 2",
      "title": "Mere Dholna Arijit Version",
      "image": "file:///android_asset/image/BhoolBhulaiyaa2.jpg",
      "link_mp3": "mp3/MereDholnaArijitVersion.mp3",
      "lyrics": ""
    }
  ]
}